octotoolkit-0.3.6.dist-info/licenses/LICENSE
octotoolkit-0.3.6.dist-info/licenses/LICENSE-TASKS
octotools/__init__.py
octotools/solver.py
octotoolkit-0.3.6.dist-info/METADATA
octotoolkit-0.3.6.dist-info/WHEEL
octotoolkit-0.3.6.dist-info/top_level.txt
octotoolkit-0.3.6.dist-info/RECORD
